{
  "title": "Microsoft Word - LTC_CLAIM_FORMS .doc",
  "outline": [
    {
      "level": "H1",
      "text": "Designation",
      "page": 1
    },
    {
      "level": "H1",
      "text": "Service",
      "page": 1
    },
    {
      "level": "H1",
      "text": "PAY + SI + NPA",
      "page": 1
    },
    {
      "level": "H1",
      "text": "Single",
      "page": 1
    },
    {
      "level": "H1",
      "text": "S.No",
      "page": 1
    },
    {
      "level": "H1",
      "text": "Name",
      "page": 1
    },
    {
      "level": "H1",
      "text": "Age",
      "page": 1
    },
    {
      "level": "H1",
      "text": "Relationship",
      "page": 1
    },
    {
      "level": "H1",
      "text": "Rs.",
      "page": 1
    },
    {
      "level": "H1",
      "text": "Date",
      "page": 1
    }
  ]
}